[
  {
    "CustomerId": 90,
    "IsClosed": false,
    "TransactionId": 2588,
    "AmountReceived": 0,
    "Balance": 20000,
    "TxnUpdatedDate": null,
    "CustomerSequenceNo": 132,
    "TxnDate": "2018-08-11T22:07:33.4698961-04:00"
  },
  {
    "CustomerId": 90,
    "IsClosed": false,
    "TransactionId": 2980,
    "AmountReceived": 1600,
    "Balance": 18400,
    "TxnUpdatedDate": null,
    "CustomerSequenceNo": 132,
    "TxnDate": "2018-08-19T22:10:17.7612992-04:00"
  },
  {
    "CustomerId": 90,
    "IsClosed": false,
    "TransactionId": 3400,
    "AmountReceived": 1400,
    "Balance": 17000,
    "TxnUpdatedDate": null,
    "CustomerSequenceNo": 132,
    "TxnDate": "2018-08-27T21:03:48.6886011-04:00"
  },
  {
    "CustomerId": 90,
    "IsClosed": false,
    "TransactionId": 3785,
    "AmountReceived": 1400,
    "Balance": 15600,
    "TxnUpdatedDate": null,
    "CustomerSequenceNo": 132,
    "TxnDate": "2018-09-03T21:42:57.2652757-04:00"
  },
  {
    "CustomerId": 90,
    "IsClosed": false,
    "TransactionId": 4147,
    "AmountReceived": 1400,
    "Balance": 14200,
    "TxnUpdatedDate": null,
    "CustomerSequenceNo": 132,
    "TxnDate": "2018-09-10T22:03:16.7213468-04:00"
  },
  {
    "CustomerId": 90,
    "IsClosed": false,
    "TransactionId": 4458,
    "AmountReceived": 1400,
    "Balance": 12800,
    "TxnUpdatedDate": null,
    "CustomerSequenceNo": 132,
    "TxnDate": "2018-09-17T21:50:25.5630529-04:00"
  },
  {
    "CustomerId": 90,
    "IsClosed": false,
    "TransactionId": 4805,
    "AmountReceived": 1400,
    "Balance": 11400,
    "TxnUpdatedDate": null,
    "CustomerSequenceNo": 132,
    "TxnDate": "2018-09-24T21:51:37.9824319-04:00"
  },
  {
    "CustomerId": 90,
    "IsClosed": false,
    "TransactionId": 5162,
    "AmountReceived": 1400,
    "Balance": 10000,
    "TxnUpdatedDate": null,
    "CustomerSequenceNo": 132,
    "TxnDate": "2018-10-01T21:47:20.6948857-04:00"
  },
  {
    "CustomerId": 90,
    "IsClosed": false,
    "TransactionId": 5544,
    "AmountReceived": 1400,
    "Balance": 8600,
    "TxnUpdatedDate": null,
    "CustomerSequenceNo": 132,
    "TxnDate": "2018-10-10T22:26:56.7423584-04:00"
  },
  {
    "CustomerId": 90,
    "IsClosed": false,
    "TransactionId": 5828,
    "AmountReceived": 1400,
    "Balance": 7200,
    "TxnUpdatedDate": null,
    "CustomerSequenceNo": 132,
    "TxnDate": "2018-10-16T21:54:07.8638032-04:00"
  },
  {
    "CustomerId": 90,
    "IsClosed": false,
    "TransactionId": 6253,
    "AmountReceived": 1400,
    "Balance": 5800,
    "TxnUpdatedDate": null,
    "CustomerSequenceNo": 132,
    "TxnDate": "2018-10-24T12:24:42.5692991-04:00"
  },
  {
    "CustomerId": 90,
    "IsClosed": false,
    "TransactionId": 6509,
    "AmountReceived": 1400,
    "Balance": 4400,
    "TxnUpdatedDate": null,
    "CustomerSequenceNo": 132,
    "TxnDate": "2018-10-30T21:38:40.2168547-04:00"
  },
  {
    "CustomerId": 90,
    "IsClosed": true,
    "TransactionId": 6571,
    "AmountReceived": 4400,
    "Balance": 0,
    "TxnUpdatedDate": null,
    "CustomerSequenceNo": 132,
    "TxnDate": "2018-10-31T13:17:20.6531164-04:00"
  }
]