[
  {
    "CustomerId": 276,
    "IsClosed": false,
    "TransactionId": 35586,
    "AmountReceived": 0,
    "Balance": 15000,
    "TxnUpdatedDate": null,
    "CustomerSequenceNo": 1000,
    "TxnDate": "2020-07-08T00:00:00",
    "SerialNo": 0,
    "Diff": 0
  },
  {
    "CustomerId": 276,
    "IsClosed": false,
    "TransactionId": 35587,
    "AmountReceived": 500,
    "Balance": 14500,
    "TxnUpdatedDate": null,
    "CustomerSequenceNo": 1000,
    "TxnDate": "2020-07-08T00:00:00",
    "SerialNo": 0,
    "Diff": 0
  },
  {
    "CustomerId": 276,
    "IsClosed": false,
    "TransactionId": 35775,
    "AmountReceived": 500,
    "Balance": 14000,
    "TxnUpdatedDate": null,
    "CustomerSequenceNo": 1000,
    "TxnDate": "2020-07-13T00:00:00",
    "SerialNo": 0,
    "Diff": 0
  },
  {
    "CustomerId": 276,
    "IsClosed": false,
    "TransactionId": 35880,
    "AmountReceived": 500,
    "Balance": 13500,
    "TxnUpdatedDate": null,
    "CustomerSequenceNo": 1000,
    "TxnDate": "2020-07-16T00:00:00",
    "SerialNo": 0,
    "Diff": 0
  },
  {
    "CustomerId": 276,
    "IsClosed": false,
    "TransactionId": 36022,
    "AmountReceived": 500,
    "Balance": 13000,
    "TxnUpdatedDate": null,
    "CustomerSequenceNo": 1000,
    "TxnDate": "2020-07-25T00:00:00",
    "SerialNo": 0,
    "Diff": 0
  },
  {
    "CustomerId": 276,
    "IsClosed": false,
    "TransactionId": 36424,
    "AmountReceived": 900,
    "Balance": 12100,
    "TxnUpdatedDate": null,
    "CustomerSequenceNo": 1000,
    "TxnDate": "2020-07-29T00:00:00",
    "SerialNo": 0,
    "Diff": 0
  },
  {
    "CustomerId": 276,
    "IsClosed": false,
    "TransactionId": 36515,
    "AmountReceived": 300,
    "Balance": 11800,
    "TxnUpdatedDate": null,
    "CustomerSequenceNo": 1000,
    "TxnDate": "2020-07-31T00:00:00",
    "SerialNo": 0,
    "Diff": 0
  },
  {
    "CustomerId": 276,
    "IsClosed": false,
    "TransactionId": 36619,
    "AmountReceived": 300,
    "Balance": 11500,
    "TxnUpdatedDate": null,
    "CustomerSequenceNo": 1000,
    "TxnDate": "2020-08-03T00:00:00",
    "SerialNo": 0,
    "Diff": 0
  },
  {
    "CustomerId": 276,
    "IsClosed": false,
    "TransactionId": 36748,
    "AmountReceived": 300,
    "Balance": 11200,
    "TxnUpdatedDate": null,
    "CustomerSequenceNo": 1000,
    "TxnDate": "2020-08-06T00:00:00",
    "SerialNo": 0,
    "Diff": 0
  },
  {
    "CustomerId": 276,
    "IsClosed": false,
    "TransactionId": 36869,
    "AmountReceived": 300,
    "Balance": 10900,
    "TxnUpdatedDate": null,
    "CustomerSequenceNo": 1000,
    "TxnDate": "2020-08-08T00:00:00",
    "SerialNo": 0,
    "Diff": 0
  },
  {
    "CustomerId": 276,
    "IsClosed": false,
    "TransactionId": 36981,
    "AmountReceived": 300,
    "Balance": 10600,
    "TxnUpdatedDate": null,
    "CustomerSequenceNo": 1000,
    "TxnDate": "2020-08-11T00:00:00",
    "SerialNo": 0,
    "Diff": 0
  },
  {
    "CustomerId": 276,
    "IsClosed": false,
    "TransactionId": 37254,
    "AmountReceived": 500,
    "Balance": 10100,
    "TxnUpdatedDate": null,
    "CustomerSequenceNo": 1000,
    "TxnDate": "2020-08-17T00:00:00",
    "SerialNo": 0,
    "Diff": 0
  },
  {
    "CustomerId": 276,
    "IsClosed": false,
    "TransactionId": 37368,
    "AmountReceived": 300,
    "Balance": 9800,
    "TxnUpdatedDate": null,
    "CustomerSequenceNo": 1000,
    "TxnDate": "2020-08-19T00:00:00",
    "SerialNo": 0,
    "Diff": 0
  },
  {
    "CustomerId": 276,
    "IsClosed": false,
    "TransactionId": 37494,
    "AmountReceived": 300,
    "Balance": 9500,
    "TxnUpdatedDate": null,
    "CustomerSequenceNo": 1000,
    "TxnDate": "2020-08-21T00:00:00",
    "SerialNo": 0,
    "Diff": 0
  },
  {
    "CustomerId": 276,
    "IsClosed": false,
    "TransactionId": 37647,
    "AmountReceived": 500,
    "Balance": 9000,
    "TxnUpdatedDate": null,
    "CustomerSequenceNo": 1000,
    "TxnDate": "2020-08-25T00:00:00",
    "SerialNo": 0,
    "Diff": 0
  },
  {
    "CustomerId": 276,
    "IsClosed": false,
    "TransactionId": 37749,
    "AmountReceived": 4200,
    "Balance": 4800,
    "TxnUpdatedDate": null,
    "CustomerSequenceNo": 1000,
    "TxnDate": "2020-08-27T00:00:00",
    "SerialNo": 0,
    "Diff": 0
  },
  {
    "CustomerId": 276,
    "IsClosed": false,
    "TransactionId": 37798,
    "AmountReceived": 4500,
    "Balance": 300,
    "TxnUpdatedDate": null,
    "CustomerSequenceNo": 1000,
    "TxnDate": "2020-08-28T00:00:00",
    "SerialNo": 0,
    "Diff": 0
  },
  {
    "CustomerId": 276,
    "IsClosed": false,
    "TransactionId": 38097,
    "AmountReceived": 0,
    "Balance": 0,
    "TxnUpdatedDate": null,
    "CustomerSequenceNo": 1000,
    "TxnDate": "2020-08-28T00:00:00",
    "SerialNo": 0,
    "Diff": 0
  }
]