[
  {
    "CustomerId": 6,
    "IsClosed": false,
    "TransactionId": 13900,
    "AmountReceived": 0,
    "Balance": 30000,
    "TxnUpdatedDate": null,
    "CustomerSequenceNo": 422,
    "TxnDate": "2019-04-01T00:00:00"
  },
  {
    "CustomerId": 6,
    "IsClosed": false,
    "TransactionId": 14179,
    "AmountReceived": 2100,
    "Balance": 27900,
    "TxnUpdatedDate": null,
    "CustomerSequenceNo": 422,
    "TxnDate": "2019-04-08T00:00:00"
  },
  {
    "CustomerId": 6,
    "IsClosed": false,
    "TransactionId": 14494,
    "AmountReceived": 2100,
    "Balance": 25800,
    "TxnUpdatedDate": null,
    "CustomerSequenceNo": 422,
    "TxnDate": "2019-04-15T00:00:00"
  },
  {
    "CustomerId": 6,
    "IsClosed": false,
    "TransactionId": 14785,
    "AmountReceived": 2100,
    "Balance": 23700,
    "TxnUpdatedDate": null,
    "CustomerSequenceNo": 422,
    "TxnDate": "2019-04-22T00:00:00"
  },
  {
    "CustomerId": 6,
    "IsClosed": false,
    "TransactionId": 15110,
    "AmountReceived": 2100,
    "Balance": 21600,
    "TxnUpdatedDate": null,
    "CustomerSequenceNo": 422,
    "TxnDate": "2019-04-29T00:00:00"
  },
  {
    "CustomerId": 6,
    "IsClosed": false,
    "TransactionId": 15424,
    "AmountReceived": 2100,
    "Balance": 19500,
    "TxnUpdatedDate": null,
    "CustomerSequenceNo": 422,
    "TxnDate": "2019-05-06T00:00:00"
  },
  {
    "CustomerId": 6,
    "IsClosed": false,
    "TransactionId": 15740,
    "AmountReceived": 2100,
    "Balance": 17400,
    "TxnUpdatedDate": null,
    "CustomerSequenceNo": 422,
    "TxnDate": "2019-05-13T00:00:00"
  },
  {
    "CustomerId": 6,
    "IsClosed": false,
    "TransactionId": 16070,
    "AmountReceived": 2100,
    "Balance": 15300,
    "TxnUpdatedDate": null,
    "CustomerSequenceNo": 422,
    "TxnDate": "2019-05-20T00:00:00"
  },
  {
    "CustomerId": 6,
    "IsClosed": false,
    "TransactionId": 16365,
    "AmountReceived": 2100,
    "Balance": 13200,
    "TxnUpdatedDate": null,
    "CustomerSequenceNo": 422,
    "TxnDate": "2019-05-27T00:00:00"
  },
  {
    "CustomerId": 6,
    "IsClosed": false,
    "TransactionId": 16688,
    "AmountReceived": 2100,
    "Balance": 11100,
    "TxnUpdatedDate": null,
    "CustomerSequenceNo": 422,
    "TxnDate": "2019-06-03T00:00:00"
  },
  {
    "CustomerId": 6,
    "IsClosed": false,
    "TransactionId": 16980,
    "AmountReceived": 2100,
    "Balance": 9000,
    "TxnUpdatedDate": null,
    "CustomerSequenceNo": 422,
    "TxnDate": "2019-06-10T00:00:00"
  },
  {
    "CustomerId": 6,
    "IsClosed": false,
    "TransactionId": 17291,
    "AmountReceived": 2100,
    "Balance": 6900,
    "TxnUpdatedDate": null,
    "CustomerSequenceNo": 422,
    "TxnDate": "2019-06-17T00:00:00"
  },
  {
    "CustomerId": 6,
    "IsClosed": false,
    "TransactionId": 17610,
    "AmountReceived": 2100,
    "Balance": 4800,
    "TxnUpdatedDate": null,
    "CustomerSequenceNo": 422,
    "TxnDate": "2019-06-24T00:00:00"
  },
  {
    "CustomerId": 6,
    "IsClosed": false,
    "TransactionId": 17948,
    "AmountReceived": 2100,
    "Balance": 2700,
    "TxnUpdatedDate": null,
    "CustomerSequenceNo": 422,
    "TxnDate": "2019-02-01T00:00:00"
  },
  {
    "CustomerId": 6,
    "IsClosed": false,
    "TransactionId": 18004,
    "AmountReceived": 2100,
    "Balance": 600,
    "TxnUpdatedDate": null,
    "CustomerSequenceNo": 422,
    "TxnDate": "2019-07-01T00:00:00"
  },
  {
    "CustomerId": 6,
    "IsClosed": true,
    "TransactionId": 18264,
    "AmountReceived": 600,
    "Balance": 0,
    "TxnUpdatedDate": null,
    "CustomerSequenceNo": 422,
    "TxnDate": "2019-07-07T00:00:00"
  }
]